lightwave_cli/__init__.py
lightwave_cli/cli.py
lightwave_cli/agents/__init__.py
lightwave_cli/agents/base.py
lightwave_cli/agents/docs.py
lightwave_cli/cli/main.py
lightwave_cli/cli/commands/__init__.py
lightwave_cli/cli/commands/task.py
lightwave_cli/formatters/task_formatter.py
lightwave_cli/tools/__init__.py
lightwave_cli/tools/docs_sync.py
lightwave_cli/tools/uv_integration.py
lightwave_cli/tools/testing/README.md
lightwave_cli/tools/testing/__init__.py
lightwave_cli/tools/testing/cli.py
lightwave_cli/tools/testing/configurator.py
lightwave_cli/tools/testing/runner.py
lightwave_cli-0.1.0.dist-info/METADATA
lightwave_cli-0.1.0.dist-info/WHEEL
lightwave_cli-0.1.0.dist-info/entry_points.txt
lightwave_cli-0.1.0.dist-info/RECORD
