Metadata-Version: 2.4
Name: lightwave-cli
Version: 0.1.0
Summary: Command-line interface for LightWave development workflows
Project-URL: Homepage, https://github.com/joelschaeffer/lightwave-cli
Project-URL: Bug Tracker, https://github.com/joelschaeffer/lightwave-cli/issues
Project-URL: Documentation, https://github.com/joelschaeffer/lightwave-eco-system-docs
Author-email: LightWave Media <info@lightwave-media.site>
License: MIT
Classifier: Development Status :: 3 - Alpha
Classifier: Intended Audience :: Developers
Classifier: License :: OSI Approved :: MIT License
Classifier: Programming Language :: Python :: 3
Classifier: Programming Language :: Python :: 3.11
Requires-Python: >=3.11
Requires-Dist: click>=8.1.7
Requires-Dist: factory-boy>=3.2.1
Requires-Dist: gitpython>=3.1.40
Requires-Dist: httpx>=0.24.1
Requires-Dist: lightwave-core>=0.1.1
Requires-Dist: pydantic-ai>=0.0.45
Requires-Dist: pydantic>=2.6.1
Requires-Dist: pytest-asyncio>=0.21.1
Requires-Dist: pytest-cov>=4.1.0
Requires-Dist: pytest-django>=4.5.2
Requires-Dist: pytest-html>=4.0.0
Requires-Dist: pytest-mock>=3.11.1
Requires-Dist: pytest-sugar>=0.9.7
Requires-Dist: pytest-timeout>=2.1.0
Requires-Dist: pytest-xdist>=3.3.1
Requires-Dist: pytest>=7.4.0
Requires-Dist: rich>=13.7.0
Requires-Dist: typer>=0.9.0
